py.typed
resolve_ec2_id.py
resolve_ec2_id-1.0.1.dist-info/entry_points.txt
resolve_ec2_id-1.0.1.dist-info/LICENSE
resolve_ec2_id-1.0.1.dist-info/WHEEL
resolve_ec2_id-1.0.1.dist-info/METADATA
resolve_ec2_id-1.0.1.dist-info/RECORD
