Metadata-Version: 2.1
Name: resolve-ec2-id
Version: 1.0.1
Summary: Look up the EC2 instance ID given an instance name.
License: MIT
Author: Ben Mares
Author-email: services-resolve-ec2-id@tensorial.com
Requires-Python: >=3.7,<4.0
Classifier: License :: OSI Approved :: MIT License
Classifier: Programming Language :: Python :: 3
Classifier: Programming Language :: Python :: 3.10
Classifier: Programming Language :: Python :: 3.7
Classifier: Programming Language :: Python :: 3.8
Classifier: Programming Language :: Python :: 3.9
Requires-Dist: typer (>=0.4.0,<0.5.0)
Requires-Dist: typing-extensions (>=4.0.1,<5.0.0); python_version < "3.8"
